PrettyGcov/CoverageMap.py
PrettyGcov/CoverageTree.py
PrettyGcov/GcovFile.py
PrettyGcov/GcovStat.py
PrettyGcov/Scanner.py
PrettyGcov/__init__.py
PrettyGcov/WebServer/PageFactory.py
PrettyGcov/WebServer/WebServer.py
PrettyGcov/WebServer/__init__.py
PrettyGcov-1.2.0.dist-info/LICENSE
PrettyGcov-1.2.0.dist-info/METADATA
PrettyGcov-1.2.0.dist-info/WHEEL
PrettyGcov-1.2.0.dist-info/top_level.txt
PrettyGcov-1.2.0.dist-info/RECORD
