Metadata-Version: 2.1
Name: PrettyGcov
Version: 1.2.0
Summary: python tools to gather, analize and visualize gcov files produced by c++ projects
Home-page: https://github.com/andreacasalino/PrettyGcov
Author: Andrea Casalino
Author-email: <andrecasa91@gmail.com>
License: UNKNOWN
Keywords: gcov,c++,coverage,gcda,gcno
Platform: UNKNOWN
Classifier: License :: OSI Approved :: MIT License
Classifier: Programming Language :: Python :: 3
License-File: LICENSE
